LICENSE.md
MANIFEST.in
README.md
setup.py
descr/__init__.py
descr/format.py
descr/highlight.py
descr/location.py
descr/registry.py
descr/rules.py
descr/rulesets.py
descr/test.py
descr/util.py
descr.egg-info/PKG-INFO
descr.egg-info/SOURCES.txt
descr.egg-info/dependency_links.txt
descr.egg-info/top_level.txt
descr/html/__init__.py
descr/html/boxy.py
descr/html/core.py
descr/html/notebook.py
descr/html/terminus.py